langchain_sap_llm/__init__.py
langchain_sap_llm/config.py
langchain_sap_llm/llms.py
langchain_sap_llm/types.py
langchain_sap_llm-0.1.1.dist-info/METADATA
langchain_sap_llm-0.1.1.dist-info/WHEEL
langchain_sap_llm-0.1.1.dist-info/RECORD
