Metadata-Version: 2.1
Name: langchain-sap-llm
Version: 0.1.1
Summary: 
Author: Teddy Xinyuan Chen
Author-email: 45612704+tddschn@users.noreply.github.com
Requires-Python: >=3.11,<4.0
Classifier: Programming Language :: Python :: 3
Classifier: Programming Language :: Python :: 3.11
Requires-Dist: langchain (>=0.0.139,<0.0.140)
Requires-Dist: requests (>=2.28.2,<3.0.0)
